{
	"$schema": "http://schema.management.azure.com/schemas/2015-01-01/deploymentTemplate.json#",
	"contentVersion": "1.0.0.0",
	"parameters": {
		"factoryName": {
			"type": "string",
			"metadata": "Data Factory name",
			"defaultValue": "labs-research"
		},
		"AzureBlobStorage1_connectionString": {
			"type": "secureString",
			"metadata": "Secure string for 'connectionString' of 'AzureBlobStorage1'"
		},
		"AzureStorageLinkedService_connectionString": {
			"type": "secureString",
			"metadata": "Secure string for 'connectionString' of 'AzureStorageLinkedService'"
		}
	},
	"variables": {
		"factoryId": "[concat('Microsoft.DataFactory/factories/', parameters('factoryName'))]"
	},
	"resources": [
		{
			"name": "[concat(parameters('factoryName'), '/CopyUpcPipeline')]",
			"type": "Microsoft.DataFactory/factories/pipelines",
			"apiVersion": "2018-06-01",
			"properties": {
				"description": "Copy Upc Pipeline",
				"activities": [
					{
						"name": "CopyFromBlobToBlob",
						"description": "Copy From Blob To Blob",
						"type": "Copy",
						"dependsOn": [],
						"policy": {
							"timeout": "7.00:00:00",
							"retry": 0,
							"retryIntervalInSeconds": 30,
							"secureOutput": false,
							"secureInput": false
						},
						"userProperties": [],
						"typeProperties": {
							"source": {
								"type": "DelimitedTextSource",
								"storeSettings": {
									"type": "AzureBlobStorageReadSettings",
									"recursive": true
								},
								"formatSettings": {
									"type": "DelimitedTextReadSettings"
								}
							},
							"sink": {
								"type": "JsonSink",
								"storeSettings": {
									"type": "AzureBlobStorageWriteSettings"
								},
								"formatSettings": {
									"type": "JsonWriteSettings",
									"quoteAllText": true
								}
							},
							"enableStaging": false
						},
						"inputs": [
							{
								"referenceName": "upcs",
								"type": "DatasetReference",
								"parameters": {}
							}
						],
						"outputs": [
							{
								"referenceName": "upcs_json",
								"type": "DatasetReference",
								"parameters": {}
							}
						]
					}
				],
				"annotations": []
			},
			"dependsOn": [
				"[concat(variables('factoryId'), '/datasets/upcs')]",
				"[concat(variables('factoryId'), '/datasets/upcs_json')]"
			]
		},
		{
			"name": "[concat(parameters('factoryName'), '/upcs')]",
			"type": "Microsoft.DataFactory/factories/datasets",
			"apiVersion": "2018-06-01",
			"properties": {
				"linkedServiceName": {
					"referenceName": "AzureStorageLinkedService",
					"type": "LinkedServiceReference"
				},
				"annotations": [],
				"type": "DelimitedText",
				"typeProperties": {
					"location": {
						"type": "AzureBlobStorageLocation",
						"fileName": "part-00002-tid-1251332733618844267-da620323-eb81-4f9f-991d-f1cb001aa645-1723-1-c000.csv",
						"container": "container-example"
					},
					"columnDelimiter": ",",
					"escapeChar": "\\",
					"firstRowAsHeader": true,
					"quoteChar": "\""
				},
				"schema": [
					{
						"name": "cid",
						"type": "String"
					},
					{
						"name": "upc",
						"type": "String"
					},
					{
						"name": "rating",
						"type": "String"
					},
					{
						"name": "ordinal_rank",
						"type": "String"
					}
				]
			},
			"dependsOn": [
				"[concat(variables('factoryId'), '/linkedServices/AzureStorageLinkedService')]"
			]
		},
		{
			"name": "[concat(parameters('factoryName'), '/upcs_json')]",
			"type": "Microsoft.DataFactory/factories/datasets",
			"apiVersion": "2018-06-01",
			"properties": {
				"linkedServiceName": {
					"referenceName": "AzureStorageLinkedService",
					"type": "LinkedServiceReference"
				},
				"annotations": [],
				"type": "Json",
				"typeProperties": {
					"location": {
						"type": "AzureBlobStorageLocation",
						"fileName": "upcsoutput.json",
						"folderPath": "output",
						"container": "container-example"
					}
				},
				"schema": {}
			},
			"dependsOn": [
				"[concat(variables('factoryId'), '/linkedServices/AzureStorageLinkedService')]"
			]
		},
		{
			"name": "[concat(parameters('factoryName'), '/AzureBlobStorage1')]",
			"type": "Microsoft.DataFactory/factories/linkedServices",
			"apiVersion": "2018-06-01",
			"properties": {
				"annotations": [],
				"type": "AzureBlobStorage",
				"typeProperties": {
					"connectionString": "[parameters('AzureBlobStorage1_connectionString')]"
				}
			},
			"dependsOn": []
		},
		{
			"name": "[concat(parameters('factoryName'), '/AzureStorageLinkedService')]",
			"type": "Microsoft.DataFactory/factories/linkedServices",
			"apiVersion": "2018-06-01",
			"properties": {
				"annotations": [],
				"type": "AzureBlobStorage",
				"typeProperties": {
					"connectionString": "[parameters('AzureStorageLinkedService_connectionString')]"
				}
			},
			"dependsOn": []
		},
		{
			"name": "[concat(parameters('factoryName'), '/triggerCopyUpc')]",
			"type": "Microsoft.DataFactory/factories/triggers",
			"apiVersion": "2018-06-01",
			"properties": {
				"annotations": [],
				"runtimeState": "Started",
				"pipeline": {
					"pipelineReference": {
						"referenceName": "CopyUpcPipeline",
						"type": "PipelineReference"
					},
					"parameters": {}
				},
				"type": "TumblingWindowTrigger",
				"typeProperties": {
					"frequency": "Minute",
					"interval": 15,
					"startTime": "2019-12-05T09:17:00.000Z",
					"delay": "00:00:00",
					"maxConcurrency": 50,
					"retryPolicy": {
						"intervalInSeconds": 30
					},
					"dependsOn": []
				}
			},
			"dependsOn": [
				"[concat(variables('factoryId'), '/pipelines/CopyUpcPipeline')]"
			]
		}
	]
}